vitalDSP/__init__.py
vitalDSP/advanced_computation/__init__.py
vitalDSP/advanced_computation/anomaly_detection.py
vitalDSP/advanced_computation/bayesian_analysis.py
vitalDSP/advanced_computation/emd.py
vitalDSP/advanced_computation/generative_signal_synthesis.py
vitalDSP/advanced_computation/harmonic_percussive_separation.py
vitalDSP/advanced_computation/kalman_filter.py
vitalDSP/advanced_computation/multimodal_fusion.py
vitalDSP/advanced_computation/neural_network_filtering.py
vitalDSP/advanced_computation/non_linear_analysis.py
vitalDSP/advanced_computation/pitch_shift.py
vitalDSP/advanced_computation/real_time_anomaly_detection.py
vitalDSP/advanced_computation/reinforcement_learning_filter.py
vitalDSP/advanced_computation/sparse_signal_processing.py
vitalDSP/feature_engineering/__init__.py
vitalDSP/feature_engineering/ecg_autonomic_features.py
vitalDSP/feature_engineering/ecg_ppg_synchronyzation_features.py
vitalDSP/feature_engineering/morphology_features.py
vitalDSP/feature_engineering/ppg_autonomic_features.py
vitalDSP/feature_engineering/ppg_light_features.py
vitalDSP/filtering/__init__.py
vitalDSP/filtering/advanced_signal_filtering.py
vitalDSP/filtering/artifact_removal.py
vitalDSP/filtering/signal_filtering.py
vitalDSP/health_analysis/__init__.py
vitalDSP/health_analysis/feature_config.yml
vitalDSP/health_analysis/file_io.py
vitalDSP/health_analysis/health_report_generator.py
vitalDSP/health_analysis/health_report_visualization.py
vitalDSP/health_analysis/html_template.py
vitalDSP/health_analysis/interpretation_engine.py
vitalDSP/ml_models/__init__.py
vitalDSP/ml_models/autoencoder.py
vitalDSP/ml_models/deep_models.py
vitalDSP/ml_models/explainability.py
vitalDSP/ml_models/feature_extractor.py
vitalDSP/ml_models/pretrained_models.py
vitalDSP/ml_models/transfer_learning.py
vitalDSP/ml_models/transformer_model.py
vitalDSP/notebooks/__init__.py
vitalDSP/notebooks/ecg.csv
vitalDSP/notebooks/ecg_small.csv
vitalDSP/notebooks/ppg.csv
vitaldsp-0.2.1.dist-info/LICENSE
vitaldsp-0.2.1.dist-info/METADATA
vitaldsp-0.2.1.dist-info/WHEEL
vitaldsp-0.2.1.dist-info/entry_points.txt
vitaldsp-0.2.1.dist-info/top_level.txt
vitaldsp-0.2.1.dist-info/RECORD
