Metadata-Version: 2.1
Name: vitaldsp
Version: 0.2.1
Summary: A comprehensive toolkit for Digital Signal Processing in healthcare applications.
Home-page: https://github.com/Oucru-Innovations/vital-DSP
Author: van-koha
Author-email: vital.data@oucru.org
License: MIT
Classifier: Programming Language :: Python :: 3
Classifier: License :: OSI Approved :: MIT License
Classifier: Operating System :: OS Independent
Classifier: Development Status :: 4 - Beta
Classifier: Intended Audience :: Developers
Classifier: Topic :: Software Development :: Libraries :: Python Modules
Classifier: Topic :: Scientific/Engineering :: Medical Science Apps.
Requires-Python: >=3.9
License-File: LICENSE
Requires-Dist: numpy (<2.0,>=1.19.2)
Requires-Dist: scipy (>=1.5.2)
Requires-Dist: plotly (>=4.14.3)
Requires-Dist: scikit-learn (>=0.23.2)
Requires-Dist: statsmodels
Requires-Dist: dash (>=2.0.0)
Requires-Dist: fastapi (>=0.68.0)
Requires-Dist: uvicorn (>=0.15.0)
Provides-Extra: all
Requires-Dist: torch (>=2.0.0) ; extra == 'all'
Requires-Dist: torchvision (>=0.15.0) ; extra == 'all'
Requires-Dist: shap (>=0.41.0) ; extra == 'all'
Requires-Dist: lime (>=0.2.0) ; extra == 'all'
Requires-Dist: tensorflow (<2.17.0,>=2.8.0) ; (platform_system != "Darwin" and python_version < "3.13") and extra == 'all'
Requires-Dist: tensorflow (<2.17.0,>=2.8.0) ; (platform_system == "Darwin" and platform_machine != "arm64" and python_version < "3.13") and extra == 'all'
Requires-Dist: tensorflow-macos (<2.17.0,>=2.8.0) ; (platform_system == "Darwin" and platform_machine == "arm64" and python_version < "3.13") and extra == 'all'
Provides-Extra: dl
Provides-Extra: dl-all
Requires-Dist: torch (>=2.0.0) ; extra == 'dl-all'
Requires-Dist: torchvision (>=0.15.0) ; extra == 'dl-all'
Requires-Dist: tensorflow (<2.17.0,>=2.8.0) ; (platform_system != "Darwin" and python_version < "3.13") and extra == 'dl-all'
Requires-Dist: tensorflow (<2.17.0,>=2.8.0) ; (platform_system == "Darwin" and platform_machine != "arm64" and python_version < "3.13") and extra == 'dl-all'
Requires-Dist: tensorflow-macos (<2.17.0,>=2.8.0) ; (platform_system == "Darwin" and platform_machine == "arm64" and python_version < "3.13") and extra == 'dl-all'
Provides-Extra: dl-pytorch
Requires-Dist: torch (>=2.0.0) ; extra == 'dl-pytorch'
Requires-Dist: torchvision (>=0.15.0) ; extra == 'dl-pytorch'
Requires-Dist: tensorflow (<2.17.0,>=2.8.0) ; (platform_system != "Darwin" and python_version < "3.13") and extra == 'dl'
Requires-Dist: tensorflow (<2.17.0,>=2.8.0) ; (platform_system == "Darwin" and platform_machine != "arm64" and python_version < "3.13") and extra == 'dl'
Requires-Dist: tensorflow-macos (<2.17.0,>=2.8.0) ; (platform_system == "Darwin" and platform_machine == "arm64" and python_version < "3.13") and extra == 'dl'
Provides-Extra: explainability
Requires-Dist: shap (>=0.41.0) ; extra == 'explainability'
Requires-Dist: lime (>=0.2.0) ; extra == 'explainability'
Provides-Extra: pytorch
Requires-Dist: torch (>=2.0.0) ; extra == 'pytorch'
Requires-Dist: torchvision (>=0.15.0) ; extra == 'pytorch'
Provides-Extra: tensorflow
Requires-Dist: tensorflow (<2.17.0,>=2.8.0) ; (platform_system != "Darwin" and python_version < "3.13") and extra == 'tensorflow'
Requires-Dist: tensorflow (<2.17.0,>=2.8.0) ; (platform_system == "Darwin" and platform_machine != "arm64" and python_version < "3.13") and extra == 'tensorflow'
Requires-Dist: tensorflow-macos (<2.17.0,>=2.8.0) ; (platform_system == "Darwin" and platform_machine == "arm64" and python_version < "3.13") and extra == 'tensorflow'
